hireherodb/__init__.py
hireherodb/models.py
hireherodb/schemas.py
hireherodb/utils.py
hireherodb-0.2.dist-info/METADATA
hireherodb-0.2.dist-info/WHEEL
hireherodb-0.2.dist-info/top_level.txt
hireherodb-0.2.dist-info/RECORD
